rpi_dht22_mqtt/__init__.py
rpi_dht22_mqtt/logger.py
rpi_dht22_mqtt-0.0.2.data/scripts/rpi-dht22-mqtt
rpi_dht22_mqtt-0.0.2.data/scripts/rpi-temperature-mqtt
rpi_dht22_mqtt-0.0.2.dist-info/DESCRIPTION.rst
rpi_dht22_mqtt-0.0.2.dist-info/METADATA
rpi_dht22_mqtt-0.0.2.dist-info/RECORD
rpi_dht22_mqtt-0.0.2.dist-info/WHEEL
rpi_dht22_mqtt-0.0.2.dist-info/metadata.json
rpi_dht22_mqtt-0.0.2.dist-info/top_level.txt
rpi_temperature_mqtt/__init__.py
rpi_temperature_mqtt/logger.py
