Metadata-Version: 2.0
Name: rpi-dht22-mqtt
Version: 0.0.2
Summary: Send temperature and humidity from DHT22 sensor to mqtt broker
Home-page: https://github.com/goodfield/rpi-dht22-mqtt.git
Author: David Uebelacker
Author-email: david@uebelacker.ch
License: The MIT License (MIT)
Requires-Dist: Adafruit-Python-DHT
Requires-Dist: paho-mqtt
